[
    {
        "contestant_names": "Enzo Camargo Lima, (1.72) VERSES Joao Vitor Scramin Do Lago, (1.95)",
        "start_time_aest": "2026-03-02T00:30:00+11:00",
        "sport_name": "Tennis",
        "competition_name": "Challenger",
        "tournamentName": "Challenger Brasilia",
        "contestants": [
            {
                "full_name": "Enzo Camargo Lima",
                "position": "HOME",
                "short_name": "Lima"
            },
            {
                "full_name": "Joao Vitor Scramin Do Lago",
                "position": "AWAY",
                "short_name": "Scramin Do Lago"
            }
        ],
        "propositions": [
            {
                "name": "Enzo Camargo Lima",
                "returnWin": 1.72
            },
            {
                "name": "Joao Vitor Scramin Do Lago",
                "returnWin": 1.95
            }
        ],
        "match_name": "Lima v Scramin Do Lago",
        "betOption": "Head To Head",
        "start_time": "2026-03-01T13:30:00.000Z"
    }
]