[
    {
        "contestant_names": "Rebecca Sramkova, (1.5) VERSES Vendula Valdmannova, (2.5)",
        "start_time_aest": "2026-02-03T20:45:00+11:00",
        "sport_name": "Tennis",
        "competition_name": "WTA",
        "contestants": [
            {
                "full_name": "Rebecca Sramkova",
                "position": "HOME",
                "short_name": "Sramkova"
            },
            {
                "full_name": "Vendula Valdmannova",
                "position": "AWAY",
                "short_name": "Valdmannova"
            }
        ],
        "propositions": [
            {
                "name": "Rebecca Sramkova",
                "returnWin": 1.5
            },
            {
                "name": "Vendula Valdmannova",
                "returnWin": 2.5
            }
        ],
        "match_name": "Sramkova v Valdmannova",
        "betOption": "Head To Head",
        "start_time": "2026-02-03T09:45:00.000Z"
    },
    {
        "contestant_names": "Changwon Sakers, (1.45) VERSES Busan Sonicboom, (2.5)",
        "start_time_aest": "2026-02-03T21:00:00+11:00",
        "sport_name": "Basketball",
        "competition_name": "South Korea KBL",
        "contestants": [
            {
                "full_name": "Changwon Sakers",
                "position": "HOME",
                "short_name": "Changwon Sakers"
            },
            {
                "full_name": "Busan Sonicboom",
                "position": "AWAY",
                "short_name": "Busan Sonicboom"
            }
        ],
        "propositions": [
            {
                "name": "Changwon Sakers",
                "returnWin": 1.45
            },
            {
                "name": "Busan Sonicboom",
                "returnWin": 2.5
            }
        ],
        "match_name": "Changwon Sakers v Busan Sonicboom",
        "betOption": "Head To Head",
        "start_time": "2026-02-03T10:00:00.000Z"
    },
    {
        "contestant_names": "Team Spirit, (1.5) VERSES Natus Vincere, (2.4)",
        "start_time_aest": "2026-02-03T21:00:00+11:00",
        "sport_name": "Esports",
        "competition_name": "DOTA2",
        "contestants": [
            {
                "full_name": "Team Spirit",
                "position": "HOME",
                "short_name": "Team Spirit"
            },
            {
                "full_name": "Natus Vincere",
                "position": "AWAY",
                "short_name": "Natus Vincere"
            }
        ],
        "propositions": [
            {
                "name": "Team Spirit",
                "returnWin": 1.5
            },
            {
                "name": "Natus Vincere",
                "returnWin": 2.4
            }
        ],
        "match_name": "Team Spirit v Natus Vincere",
        "betOption": "Head To Head",
        "start_time": "2026-02-03T10:00:00.000Z"
    },
    {
        "contestant_names": "Sergio Callejon Hernando, (2.5) VERSES Pol Martin Tiffon, (1.46)",
        "start_time_aest": "2026-02-03T21:00:00+11:00",
        "sport_name": "Tennis",
        "competition_name": "Challenger",
        "contestants": [
            {
                "full_name": "Sergio Callejon Hernando",
                "position": "HOME",
                "short_name": "Callejn Hernando"
            },
            {
                "full_name": "Pol Martin Tiffon",
                "position": "AWAY",
                "short_name": "Martin Tiffon"
            }
        ],
        "propositions": [
            {
                "name": "Sergio Callejon Hernando",
                "returnWin": 2.5
            },
            {
                "name": "Pol Martin Tiffon",
                "returnWin": 1.46
            }
        ],
        "match_name": "Callejn Hernando v Martin Tiffon",
        "betOption": "Head To Head",
        "start_time": "2026-02-03T10:00:00.000Z"
    },
    {
        "contestant_names": "Sara Cakarevic, (1.48) VERSES Oceane Babel, (2.5)",
        "start_time_aest": "2026-02-03T21:00:00+11:00",
        "sport_name": "Tennis",
        "competition_name": "ITF Womens",
        "contestants": [
            {
                "full_name": "Sara Cakarevic",
                "position": "HOME",
                "short_name": "Cakarevic"
            },
            {
                "full_name": "Oceane Babel",
                "position": "AWAY",
                "short_name": "Babel"
            }
        ],
        "propositions": [
            {
                "name": "Sara Cakarevic",
                "returnWin": 1.48
            },
            {
                "name": "Oceane Babel",
                "returnWin": 2.5
            }
        ],
        "match_name": "Cakarevic v Babel",
        "betOption": "Head To Head",
        "start_time": "2026-02-03T10:00:00.000Z"
    },
    {
        "contestant_names": "Corley/Corley, (1.65) VERSES Cavalle-Reimers/Moratelli, (2.15)",
        "start_time_aest": "2026-02-03T21:00:00+11:00",
        "sport_name": "Tennis",
        "competition_name": "WTA Doubles",
        "contestants": [
            {
                "full_name": "Corley/Corley",
                "position": "HOME",
                "short_name": "Corley/Corley"
            },
            {
                "full_name": "Cavalle-Reimers/Moratelli",
                "position": "AWAY",
                "short_name": "C-Reimers/Moratelli"
            }
        ],
        "propositions": [
            {
                "name": "Corley/Corley",
                "returnWin": 1.65
            },
            {
                "name": "Cavalle-Reimers/Moratelli",
                "returnWin": 2.15
            }
        ],
        "match_name": "Corley/Corley v C-Reimers/Moratelli",
        "betOption": "Head To Head",
        "start_time": "2026-02-03T10:00:00.000Z"
    },
    {
        "contestant_names": "Fujairah, (2.4) VERSES Ajman, (1.55)",
        "start_time_aest": "2026-02-03T22:00:00+11:00",
        "sport_name": "Cricket",
        "competition_name": "Emirates D10",
        "contestants": [
            {
                "full_name": "Fujairah",
                "position": "HOME",
                "short_name": "Fujairah"
            },
            {
                "full_name": "Ajman",
                "position": "AWAY",
                "short_name": "Ajman"
            }
        ],
        "propositions": [
            {
                "name": "Fujairah",
                "returnWin": 2.4
            },
            {
                "name": "Ajman",
                "returnWin": 1.55
            }
        ],
        "match_name": "Fujairah v Ajman",
        "betOption": "Head To Head",
        "start_time": "2026-02-03T11:00:00.000Z"
    },
    {
        "contestant_names": "OG, (2.15) VERSES Team Liquid, (1.62)",
        "start_time_aest": "2026-02-03T22:00:00+11:00",
        "sport_name": "Esports",
        "competition_name": "DOTA2",
        "contestants": [
            {
                "full_name": "OG",
                "position": "HOME",
                "short_name": "Og"
            },
            {
                "full_name": "Team Liquid",
                "position": "AWAY",
                "short_name": "Team Liquid"
            }
        ],
        "propositions": [
            {
                "name": "OG",
                "returnWin": 2.15
            },
            {
                "name": "Team Liquid",
                "returnWin": 1.62
            }
        ],
        "match_name": "Og v Team Liquid",
        "betOption": "Head To Head",
        "start_time": "2026-02-03T11:00:00.000Z"
    },
    {
        "contestant_names": "Andrea Guerrieri, (1.58) VERSES Niels Visker, (2.25)",
        "start_time_aest": "2026-02-03T22:00:00+11:00",
        "sport_name": "Tennis",
        "competition_name": "Challenger",
        "contestants": [
            {
                "full_name": "Andrea Guerrieri",
                "position": "HOME",
                "short_name": "Guerrieri A"
            },
            {
                "full_name": "Niels Visker",
                "position": "AWAY",
                "short_name": "Visker"
            }
        ],
        "propositions": [
            {
                "name": "Andrea Guerrieri",
                "returnWin": 1.58
            },
            {
                "name": "Niels Visker",
                "returnWin": 2.25
            }
        ],
        "match_name": "Guerrieri A v Visker",
        "betOption": "Head To Head",
        "start_time": "2026-02-03T11:00:00.000Z"
    },
    {
        "contestant_names": "Mats Rosenkranz, (1.46) VERSES Patrick Zahraj, (2.5)",
        "start_time_aest": "2026-02-03T22:00:00+11:00",
        "sport_name": "Tennis",
        "competition_name": "Challenger",
        "contestants": [
            {
                "full_name": "Mats Rosenkranz",
                "position": "HOME",
                "short_name": "Rosenkranz"
            },
            {
                "full_name": "Patrick Zahraj",
                "position": "AWAY",
                "short_name": "Zahraj"
            }
        ],
        "propositions": [
            {
                "name": "Mats Rosenkranz",
                "returnWin": 1.46
            },
            {
                "name": "Patrick Zahraj",
                "returnWin": 2.5
            }
        ],
        "match_name": "Rosenkranz v Zahraj",
        "betOption": "Head To Head",
        "start_time": "2026-02-03T11:00:00.000Z"
    },
    {
        "contestant_names": "McCartney Kessler, (2.1) VERSES Leylah Annie Fernandez, (1.7)",
        "start_time_aest": "2026-02-03T22:00:00+11:00",
        "sport_name": "Tennis",
        "competition_name": "WTA",
        "contestants": [
            {
                "full_name": "McCartney Kessler",
                "position": "HOME",
                "short_name": "Kessler"
            },
            {
                "full_name": "Leylah Annie Fernandez",
                "position": "AWAY",
                "short_name": "Fernandez L"
            }
        ],
        "propositions": [
            {
                "name": "McCartney Kessler",
                "returnWin": 2.1
            },
            {
                "name": "Leylah Annie Fernandez",
                "returnWin": 1.7
            }
        ],
        "match_name": "Kessler v Fernandez L",
        "betOption": "Head To Head",
        "start_time": "2026-02-03T11:00:00.000Z"
    }
]