[
    {
        "contestant_names": "Stefan Kozlov, (1.75) VERSES Rodrigo Pacheco Mendez, (1.95)",
        "start_time_aest": "2026-02-21T08:30:00+11:00",
        "sport_name": "Tennis",
        "competition_name": "Challenger",
        "contestants": [
            {
                "full_name": "Stefan Kozlov",
                "position": "HOME",
                "short_name": "Kozlov S"
            },
            {
                "full_name": "Rodrigo Pacheco Mendez",
                "position": "AWAY",
                "short_name": "Pacheco Mendez"
            }
        ],
        "propositions": [
            {
                "name": "Stefan Kozlov",
                "returnWin": 1.75
            },
            {
                "name": "Rodrigo Pacheco Mendez",
                "returnWin": 1.95
            }
        ],
        "match_name": "Kozlov S v Pacheco Mendez",
        "betOption": "Head To Head",
        "start_time": "2026-02-20T21:30:00.000Z"
    },
    {
        "contestant_names": "Sao Jose Dos Cam, (1.52) VERSES SC Corinthians, (2.3)",
        "start_time_aest": "2026-02-21T09:30:00+11:00",
        "sport_name": "Basketball",
        "competition_name": "Brazil NBB",
        "contestants": [
            {
                "full_name": "Sao Jose Dos Cam",
                "position": "HOME",
                "short_name": "Sao Jose Dos Cam"
            },
            {
                "full_name": "SC Corinthians",
                "position": "AWAY",
                "short_name": "SC Corinthians"
            }
        ],
        "propositions": [
            {
                "name": "Sao Jose Dos Cam",
                "returnWin": 1.52
            },
            {
                "name": "SC Corinthians",
                "returnWin": 2.3
            }
        ],
        "match_name": "Sao Jose Dos Cam v SC Corinthians",
        "betOption": "Head To Head",
        "start_time": "2026-02-20T22:30:00.000Z"
    },
    {
        "contestant_names": "Learner Tien, (1.52) VERSES Frances Tiafoe, (2.4)",
        "start_time_aest": "2026-02-21T10:00:00+11:00",
        "sport_name": "Tennis",
        "competition_name": "ATP",
        "contestants": [
            {
                "full_name": "Learner Tien",
                "position": "HOME",
                "short_name": "Tien L"
            },
            {
                "full_name": "Frances Tiafoe",
                "position": "AWAY",
                "short_name": "Tiafoe"
            }
        ],
        "propositions": [
            {
                "name": "Learner Tien",
                "returnWin": 1.52
            },
            {
                "name": "Frances Tiafoe",
                "returnWin": 2.4
            }
        ],
        "match_name": "Tien L v Tiafoe",
        "betOption": "Head To Head",
        "start_time": "2026-02-20T23:00:00.000Z"
    },
    {
        "contestant_names": "Schnaitter/Wallner, (2.1) VERSES Melo/Fonseca, (1.68)",
        "start_time_aest": "2026-02-21T10:00:00+11:00",
        "sport_name": "Tennis",
        "competition_name": "ATP Doubles",
        "contestants": [
            {
                "full_name": "Schnaitter/Wallner",
                "position": "HOME",
                "short_name": "Schnaitter/Wallner"
            },
            {
                "full_name": "Melo/Fonseca",
                "position": "AWAY",
                "short_name": "Melo/Fonseca"
            }
        ],
        "propositions": [
            {
                "name": "Schnaitter/Wallner",
                "returnWin": 2.1
            },
            {
                "name": "Melo/Fonseca",
                "returnWin": 1.68
            }
        ],
        "match_name": "Schnaitter/Wallner v Melo/Fonseca",
        "betOption": "Head To Head",
        "start_time": "2026-02-20T23:00:00.000Z"
    }
]