[
    {
        "contestant_names_odds": "Robin Bertrand, (1.75) VERSES Christian Langmo, (1.95)",
        "contestant_names": "Robin Bertrand VERSES Christian Langmo",
        "start_time_aest": "2026-03-10T21:00:00+11:00",
        "sport_name": "Tennis",
        "competition_name": "Challenger",
        "tournamentName": "Challenger Hersonissos 2",
        "contestants": [
            {
                "full_name": "Robin Bertrand",
                "position": "HOME",
                "short_name": "Bertrand R"
            },
            {
                "full_name": "Christian Langmo",
                "position": "AWAY",
                "short_name": "Langmo C"
            }
        ],
        "propositions": [
            {
                "name": "Robin Bertrand",
                "returnWin": 1.75
            },
            {
                "name": "Christian Langmo",
                "returnWin": 1.95
            }
        ],
        "match_name": "Bertrand R v Langmo C",
        "betOption": "Head To Head",
        "start_time": "2026-03-10T10:00:00.000Z"
    },
    {
        "contestant_names_odds": "Alexander Donski, (1.75) VERSES Garrett Johns, (1.95)",
        "contestant_names": "Alexander Donski VERSES Garrett Johns",
        "start_time_aest": "2026-03-10T21:00:00+11:00",
        "sport_name": "Tennis",
        "competition_name": "Challenger",
        "tournamentName": "Challenger Kigali 2",
        "contestants": [
            {
                "full_name": "Alexander Donski",
                "position": "HOME",
                "short_name": "Donski"
            },
            {
                "full_name": "Garrett Johns",
                "position": "AWAY",
                "short_name": "Johns G"
            }
        ],
        "propositions": [
            {
                "name": "Alexander Donski",
                "returnWin": 1.75
            },
            {
                "name": "Garrett Johns",
                "returnWin": 1.95
            }
        ],
        "match_name": "Donski v Johns G",
        "betOption": "Head To Head",
        "start_time": "2026-03-10T10:00:00.000Z"
    },
    {
        "contestant_names_odds": "Alexandre Aubriot, (1.8) VERSES Finn Murgett, (1.9)",
        "contestant_names": "Alexandre Aubriot VERSES Finn Murgett",
        "start_time_aest": "2026-03-10T21:00:00+11:00",
        "sport_name": "Tennis",
        "competition_name": "ITF Mens",
        "tournamentName": "ITFM Monastir",
        "contestants": [
            {
                "full_name": "Alexandre Aubriot",
                "position": "HOME",
                "short_name": "Aubriot A"
            },
            {
                "full_name": "Finn Murgett",
                "position": "AWAY",
                "short_name": "Murgett"
            }
        ],
        "propositions": [
            {
                "name": "Alexandre Aubriot",
                "returnWin": 1.8
            },
            {
                "name": "Finn Murgett",
                "returnWin": 1.9
            }
        ],
        "match_name": "Aubriot A v Murgett",
        "betOption": "Head To Head",
        "start_time": "2026-03-10T10:00:00.000Z"
    },
    {
        "contestant_names_odds": "Erjavec/Udvardy, (1.95) VERSES Kempen/Pridankina, (1.75)",
        "contestant_names": "Erjavec/Udvardy VERSES Kempen/Pridankina",
        "start_time_aest": "2026-03-10T21:00:00+11:00",
        "sport_name": "Tennis",
        "competition_name": "WTA 125 Doubles",
        "tournamentName": "WTA 125 Antalya 3 Doubles",
        "contestants": [
            {
                "full_name": "Erjavec/Udvardy",
                "position": "HOME",
                "short_name": "Erjavec/Udvardy"
            },
            {
                "full_name": "Kempen/Pridankina",
                "position": "AWAY",
                "short_name": "Kempen/Pridankina"
            }
        ],
        "propositions": [
            {
                "name": "Erjavec/Udvardy",
                "returnWin": 1.95
            },
            {
                "name": "Kempen/Pridankina",
                "returnWin": 1.75
            }
        ],
        "match_name": "Erjavec/Udvardy v Kempen/Pridankina",
        "betOption": "Head To Head",
        "start_time": "2026-03-10T10:00:00.000Z"
    }
]