[
    {
        "contestant_names": "PGE Skra Belchatow, (1.9) VERSES Lotos Trefl Gdansk, (1.8)",
        "start_time_aest": "2026-03-02T00:45:00+11:00",
        "sport_name": "Volleyball",
        "competition_name": "Poland PlusLiga Men",
        "contestants": [
            {
                "full_name": "PGE Skra Belchatow",
                "position": "HOME",
                "short_name": "PGE SkraBelchtw"
            },
            {
                "full_name": "Lotos Trefl Gdansk",
                "position": "AWAY",
                "short_name": "Trefl Gdansk"
            }
        ],
        "propositions": [
            {
                "name": "PGE Skra Belchatow",
                "returnWin": 1.9
            },
            {
                "name": "Lotos Trefl Gdansk",
                "returnWin": 1.8
            }
        ],
        "match_name": "PGE SkraBelchtw v Trefl Gdansk",
        "betOption": "Head To Head",
        "start_time": "2026-03-01T13:45:00.000Z"
    }
]