[
    {
        "contestant_names_prop": "Internazionale, (1.5) VERSES Como, (2.5)",
        "contestant_names": "Internazionale VERSES Como",
        "start_time_aest": "2026-04-22T05:00:00+10:00",
        "sport_name": "Soccer",
        "competition_name": "Italy Cup",
        "contestants": [
            {
                "full_name": "Internazionale",
                "position": "HOME",
                "short_name": "Internazionale"
            },
            {
                "full_name": "Como",
                "position": "AWAY",
                "short_name": "Como"
            }
        ],
        "match_name": "Internazionale v Como",
        "match_shortName": "ICP Inter-Como WnrOfTie",
        "start_time": "2026-04-21T19:00:00.000Z"
    }
]