[
    {
        "contestant_names": "Gargzdai, (1.52) VERSES Nevezis, (2.35)",
        "start_time_aest": "2026-03-08T04:10:00+11:00",
        "sport_name": "Basketball",
        "competition_name": "Lithuania LKL",
        "contestants": [
            {
                "full_name": "Gargzdai",
                "position": "HOME",
                "short_name": "Gargzdai"
            },
            {
                "full_name": "Nevezis",
                "position": "AWAY",
                "short_name": "Nevezis"
            }
        ],
        "propositions": [
            {
                "name": "Gargzdai",
                "returnWin": 1.52
            },
            {
                "name": "Nevezis",
                "returnWin": 2.35
            }
        ],
        "match_name": "Gargzdai v Nevezis",
        "betOption": "Head To Head",
        "start_time": "2026-03-07T17:10:00.000Z"
    },
    {
        "contestant_names": "Gavin Young, (1.65) VERSES Quinn Vandecasteele, (2.1)",
        "start_time_aest": "2026-03-08T04:30:00+11:00",
        "sport_name": "Tennis",
        "competition_name": "ITF Mens",
        "tournamentName": "ITFM Sherbrooke",
        "contestants": [
            {
                "full_name": "Gavin Young",
                "position": "HOME",
                "short_name": "Young G"
            },
            {
                "full_name": "Quinn Vandecasteele",
                "position": "AWAY",
                "short_name": "Vandecasteele"
            }
        ],
        "propositions": [
            {
                "name": "Gavin Young",
                "returnWin": 1.65
            },
            {
                "name": "Quinn Vandecasteele",
                "returnWin": 2.1
            }
        ],
        "match_name": "Young G v Vandecasteele",
        "betOption": "Head To Head",
        "start_time": "2026-03-07T17:30:00.000Z"
    },
    {
        "contestant_names": "Chen B Y/Liu Y, (2.3) VERSES Chia A/Soh W Y, (1.55)",
        "start_time_aest": "2026-03-08T04:45:00+11:00",
        "sport_name": "Badminton",
        "competition_name": "Badminton World Tour Doubles",
        "tournamentName": "All England Open Mens Doubles",
        "contestants": [
            {
                "full_name": "Chen B Y/Liu Y",
                "position": "HOME",
                "short_name": "Chen B Y/Liu Y"
            },
            {
                "full_name": "Chia A/Soh W Y",
                "position": "AWAY",
                "short_name": "Chi A/Soh W"
            }
        ],
        "propositions": [
            {
                "name": "Chen B Y/Liu Y",
                "returnWin": 2.3
            },
            {
                "name": "Chia A/Soh W Y",
                "returnWin": 1.55
            }
        ],
        "match_name": "Chen B Y/Liu Y v Chi A/Soh W",
        "betOption": "Head To Head",
        "start_time": "2026-03-07T17:45:00.000Z"
    }
]