[
    {
        "contestant_names": "Camilo Ugo Carabelli, (2.5) VERSES Sebastian Baez, (1.5)",
        "start_time_aest": "2026-02-14T08:45:00+11:00",
        "sport_name": "Tennis",
        "competition_name": "ATP",
        "contestants": [
            {
                "full_name": "Camilo Ugo Carabelli",
                "position": "HOME",
                "short_name": "Ugo Carabelli"
            },
            {
                "full_name": "Sebastian Baez",
                "position": "AWAY",
                "short_name": "Baez"
            }
        ],
        "propositions": [
            {
                "name": "Camilo Ugo Carabelli",
                "returnWin": 2.5
            },
            {
                "name": "Sebastian Baez",
                "returnWin": 1.5
            }
        ],
        "match_name": "Ugo Carabelli v Baez",
        "betOption": "Head To Head",
        "start_time": "2026-02-13T21:45:00.000Z"
    },
    {
        "contestant_names": "UniaoCorinthians, (2.5) VERSES PinheirosSKY, (1.45)",
        "start_time_aest": "2026-02-14T09:30:00+11:00",
        "sport_name": "Basketball",
        "competition_name": "Brazil NBB",
        "contestants": [
            {
                "full_name": "UniaoCorinthians",
                "position": "HOME",
                "short_name": "UniaoCorinthians"
            },
            {
                "full_name": "PinheirosSKY",
                "position": "AWAY",
                "short_name": "PinheirosSKY"
            }
        ],
        "propositions": [
            {
                "name": "UniaoCorinthians",
                "returnWin": 2.5
            },
            {
                "name": "PinheirosSKY",
                "returnWin": 1.45
            }
        ],
        "match_name": "UniaoCorinthians v PinheirosSKY",
        "betOption": "Head To Head",
        "start_time": "2026-02-13T22:30:00.000Z"
    },
    {
        "contestant_names": "Caxias Do Sul, (2.25) VERSES Paulistano, (1.55)",
        "start_time_aest": "2026-02-14T09:30:00+11:00",
        "sport_name": "Basketball",
        "competition_name": "Brazil NBB",
        "contestants": [
            {
                "full_name": "Caxias Do Sul",
                "position": "HOME",
                "short_name": "Caxias Do Sul"
            },
            {
                "full_name": "Paulistano",
                "position": "AWAY",
                "short_name": "Paulistano"
            }
        ],
        "propositions": [
            {
                "name": "Caxias Do Sul",
                "returnWin": 2.25
            },
            {
                "name": "Paulistano",
                "returnWin": 1.55
            }
        ],
        "match_name": "Caxias Do Sul v Paulistano",
        "betOption": "Head To Head",
        "start_time": "2026-02-13T22:30:00.000Z"
    },
    {
        "contestant_names": "Rivadavia De Men, (2.1) VERSES Paula Galvez, (1.62)",
        "start_time_aest": "2026-02-14T11:00:00+11:00",
        "sport_name": "Basketball",
        "competition_name": "Argentina Liga A",
        "contestants": [
            {
                "full_name": "Rivadavia De Men",
                "position": "HOME",
                "short_name": "Rivadavia De Men"
            },
            {
                "full_name": "Paula Galvez",
                "position": "AWAY",
                "short_name": "Paula Galvez"
            }
        ],
        "propositions": [
            {
                "name": "Rivadavia De Men",
                "returnWin": 2.1
            },
            {
                "name": "Paula Galvez",
                "returnWin": 1.62
            }
        ],
        "match_name": "Rivadavia De Men v Paula Galvez",
        "betOption": "Head To Head",
        "start_time": "2026-02-14T00:00:00.000Z"
    }
]