[
    {
        "contestant_names": "August Holmgren, (2.4) VERSES Sascha Gueymard Wayenburg, (1.5)",
        "start_time_aest": "2026-02-17T05:45:00+11:00",
        "sport_name": "Tennis",
        "competition_name": "Challenger",
        "contestants": [
            {
                "full_name": "August Holmgren",
                "position": "HOME",
                "short_name": "Holmgren"
            },
            {
                "full_name": "Sascha Gueymard Wayenburg",
                "position": "AWAY",
                "short_name": "Gueymard"
            }
        ],
        "propositions": [
            {
                "name": "August Holmgren",
                "returnWin": 2.4
            },
            {
                "name": "Sascha Gueymard Wayenburg",
                "returnWin": 1.5
            }
        ],
        "match_name": "Holmgren v Gueymard",
        "betOption": "Head To Head",
        "start_time": "2026-02-16T18:45:00.000Z"
    },
    {
        "contestant_names": "Radomka Radom (W), (2.15) VERSES MKS Sokol Mogilno (W), (1.62)",
        "start_time_aest": "2026-02-17T06:00:00+11:00",
        "sport_name": "Volleyball",
        "competition_name": "Tauron Liga Women",
        "contestants": [
            {
                "full_name": "Radomka Radom (W)",
                "position": "HOME",
                "short_name": "RadomkaRadom (W)"
            },
            {
                "full_name": "MKS Sokol Mogilno (W)",
                "position": "AWAY",
                "short_name": "SokolMogilno (W)"
            }
        ],
        "propositions": [
            {
                "name": "Radomka Radom (W)",
                "returnWin": 2.15
            },
            {
                "name": "MKS Sokol Mogilno (W)",
                "returnWin": 1.62
            }
        ],
        "match_name": "RadomkaRadom (W) v SokolMogilno (W)",
        "betOption": "Head To Head",
        "start_time": "2026-02-16T19:00:00.000Z"
    },
    {
        "contestant_names": "Cristian Garin, (1.85) VERSES Thiago Agustin Tirante, (1.95)",
        "start_time_aest": "2026-02-17T06:30:00+11:00",
        "sport_name": "Tennis",
        "competition_name": "ATP",
        "contestants": [
            {
                "full_name": "Cristian Garin",
                "position": "HOME",
                "short_name": "Garin C"
            },
            {
                "full_name": "Thiago Agustin Tirante",
                "position": "AWAY",
                "short_name": "Tirante"
            }
        ],
        "propositions": [
            {
                "name": "Cristian Garin",
                "returnWin": 1.85
            },
            {
                "name": "Thiago Agustin Tirante",
                "returnWin": 1.95
            }
        ],
        "match_name": "Garin C v Tirante",
        "betOption": "Head To Head",
        "start_time": "2026-02-16T19:30:00.000Z"
    },
    {
        "contestant_names": "Sebastian Ofner, (2.5) VERSES Hugo Gaston, (1.46)",
        "start_time_aest": "2026-02-17T06:30:00+11:00",
        "sport_name": "Tennis",
        "competition_name": "Challenger",
        "contestants": [
            {
                "full_name": "Sebastian Ofner",
                "position": "HOME",
                "short_name": "Ofner S"
            },
            {
                "full_name": "Hugo Gaston",
                "position": "AWAY",
                "short_name": "Gaston"
            }
        ],
        "propositions": [
            {
                "name": "Sebastian Ofner",
                "returnWin": 2.5
            },
            {
                "name": "Hugo Gaston",
                "returnWin": 1.46
            }
        ],
        "match_name": "Ofner S v Gaston",
        "betOption": "Head To Head",
        "start_time": "2026-02-16T19:30:00.000Z"
    }
]