[
    {
        "contestant_names": "G2, (1.7) VERSES FaZe, (2)",
        "start_time_aest": "2026-03-07T02:30:00+11:00",
        "sport_name": "Esports",
        "competition_name": "Counter Strike 2",
        "tournamentName": "CS2 - ESL Pro League Play In",
        "contestants": [
            {
                "full_name": "G2",
                "position": "HOME",
                "short_name": "G2"
            },
            {
                "full_name": "FaZe",
                "position": "AWAY",
                "short_name": "FaZe"
            }
        ],
        "propositions": [
            {
                "name": "G2",
                "returnWin": 1.7
            },
            {
                "name": "FaZe",
                "returnWin": 2
            }
        ],
        "match_name": "G2 v FaZe",
        "betOption": "Head To Head",
        "start_time": "2026-03-06T15:30:00.000Z"
    },
    {
        "contestant_names": "Pisek Srsni, (2.4) VERSES Pardubice, (1.48)",
        "start_time_aest": "2026-03-07T03:00:00+11:00",
        "sport_name": "Basketball",
        "competition_name": "Czech Republic NBL",
        "contestants": [
            {
                "full_name": "Pisek Srsni",
                "position": "HOME",
                "short_name": "Pisek Srsni"
            },
            {
                "full_name": "Pardubice",
                "position": "AWAY",
                "short_name": "Pardubice"
            }
        ],
        "propositions": [
            {
                "name": "Pisek Srsni",
                "returnWin": 2.4
            },
            {
                "name": "Pardubice",
                "returnWin": 1.48
            }
        ],
        "match_name": "Pisek Srsni v Pardubice",
        "betOption": "Head To Head",
        "start_time": "2026-03-06T16:00:00.000Z"
    },
    {
        "contestant_names": "Hugo Gaston, (1.62) VERSES Michael Kouame, (2.15)",
        "start_time_aest": "2026-03-07T03:00:00+11:00",
        "sport_name": "Tennis",
        "competition_name": "Challenger",
        "tournamentName": "Challenger Thionville",
        "contestants": [
            {
                "full_name": "Hugo Gaston",
                "position": "HOME",
                "short_name": "Gaston"
            },
            {
                "full_name": "Michael Kouame",
                "position": "AWAY",
                "short_name": "Kouame"
            }
        ],
        "propositions": [
            {
                "name": "Hugo Gaston",
                "returnWin": 1.62
            },
            {
                "name": "Michael Kouame",
                "returnWin": 2.15
            }
        ],
        "match_name": "Gaston v Kouame",
        "betOption": "Head To Head",
        "start_time": "2026-03-06T16:00:00.000Z"
    }
]