[
    {
        "contestant_names_prop": "Gimle BBK, (2) VERSES Fyllingen, (1.7)",
        "contestant_names": "Gimle BBK VERSES Fyllingen",
        "start_time_aest": "2026-04-22T03:00:00+10:00",
        "sport_name": "Basketball",
        "competition_name": "Norway BLNO",
        "contestants": [
            {
                "full_name": "Gimle BBK",
                "position": "HOME",
                "short_name": "Gimle BBK"
            },
            {
                "full_name": "Fyllingen",
                "position": "AWAY",
                "short_name": "Fyllingen"
            }
        ],
        "match_name": "Gimle BBK v Fyllingen",
        "match_shortName": "Nor Giml-Flgn Hd to Hd",
        "start_time": "2026-04-21T17:00:00.000Z"
    },
    {
        "contestant_names_prop": "Eskilstuna Bbk, (2.2) VERSES KFUM Fryshuset, (1.57)",
        "contestant_names": "Eskilstuna Bbk VERSES KFUM Fryshuset",
        "start_time_aest": "2026-04-22T03:00:00+10:00",
        "sport_name": "Basketball",
        "competition_name": "Sweden Superettan",
        "contestants": [
            {
                "full_name": "Eskilstuna Bbk",
                "position": "HOME",
                "short_name": "Eskilstuna Bbk"
            },
            {
                "full_name": "KFUM Fryshuset",
                "position": "AWAY",
                "short_name": "KFUM Fryshuset"
            }
        ],
        "match_name": "Eskilstuna Bbk v KFUM Fryshuset",
        "match_shortName": "Sw2 Eski-KFFh Hd to Hd",
        "start_time": "2026-04-21T17:00:00.000Z"
    }
]